blackjack/__init__.py
blackjack/__main__.py
blackjack/action.py
blackjack/deck.py
blackjack/exceptions.py
blackjack/game.py
blackjack/game_setup.py
blackjack/player.py
play_blackjack-0.1.1.dist-info/LICENSE
play_blackjack-0.1.1.dist-info/WHEEL
play_blackjack-0.1.1.dist-info/METADATA
play_blackjack-0.1.1.dist-info/RECORD
