Metadata-Version: 2.1
Name: play-blackjack
Version: 0.1.1
Summary: Command Line Single-player game of Blackjack
Keywords: blackjack,games,cards
Author: Ben Griffith
Requires-Python: >=3.9
Classifier: License :: OSI Approved :: MIT License
Requires-Dist: pytest ; extra == "test"
Project-URL: Source, https://github.com/bengriffith/blackjack
Provides-Extra: test
